odoo/addons/account_type_menu/README.rst
odoo/addons/account_type_menu/__init__.py
odoo/addons/account_type_menu/__manifest__.py
odoo/addons/account_type_menu/i18n/account_type_menu.pot
odoo/addons/account_type_menu/i18n/ar.po
odoo/addons/account_type_menu/i18n/de.po
odoo/addons/account_type_menu/i18n/fr.po
odoo/addons/account_type_menu/i18n/hr.po
odoo/addons/account_type_menu/i18n/nl_NL.po
odoo/addons/account_type_menu/i18n/tr.po
odoo/addons/account_type_menu/static/description/icon.png
odoo/addons/account_type_menu/views/account_type.xml
odoo11_addon_account_type_menu-11.0.1.0.0.99.dev7.dist-info/METADATA
odoo11_addon_account_type_menu-11.0.1.0.0.99.dev7.dist-info/RECORD
odoo11_addon_account_type_menu-11.0.1.0.0.99.dev7.dist-info/WHEEL
odoo11_addon_account_type_menu-11.0.1.0.0.99.dev7.dist-info/top_level.txt
